LICENSE
setup.py
worldofbugs/__init__.py
worldofbugs/__main__.py
worldofbugs/_entry_point.py
worldofbugs/dataset.py
worldofbugs.egg-info/PKG-INFO
worldofbugs.egg-info/SOURCES.txt
worldofbugs.egg-info/dependency_links.txt
worldofbugs.egg-info/entry_points.txt
worldofbugs.egg-info/not-zip-safe
worldofbugs.egg-info/requires.txt
worldofbugs.egg-info/top_level.txt
worldofbugs/environment/__init__.py
worldofbugs/environment/_action.py
worldofbugs/environment/_base.py
worldofbugs/environment/_environment.py
worldofbugs/environment/_observation.py
worldofbugs/environment/sidechannel.py
worldofbugs/test/__init__.py
worldofbugs/test/__test__.py
worldofbugs/test/lint.py
worldofbugs/test/make_badge.py
worldofbugs/test/test_editor.py
worldofbugs/test/unity-test.py
worldofbugs/test/unit/__init__.py
worldofbugs/test/unit/test_action.py
worldofbugs/test/unit/test_environment.py
worldofbugs/test/unit/test_observation.py
worldofbugs/test/unit/test_sidechannel.py
worldofbugs/test/unit/test_utils.py
worldofbugs/test/utils/__init__.py
worldofbugs/test/utils/config.py
worldofbugs/utils/__init__.py
worldofbugs/utils/_build.py
worldofbugs/utils/_utils.py