Metadata-Version: 2.1
Name: worldofbugs
Version: 0.0.1
Summary: World of Bugs (WOB) is a platform that supports research in Automated Bug Detection (ABD) in video games.
Home-page: https://benedictwilkins.github.io/world-of-bugs/
Author: Benedict Wilkins
Author-email: benrjw@gmail.com
License: UNKNOWN
Platform: UNKNOWN
License-File: LICENSE
